AAUtility/__init__.py
AAUtility/hello.py
AAUtility-1.0.2.dist-info/DESCRIPTION.rst
AAUtility-1.0.2.dist-info/METADATA
AAUtility-1.0.2.dist-info/RECORD
AAUtility-1.0.2.dist-info/WHEEL
AAUtility-1.0.2.dist-info/metadata.json
AAUtility-1.0.2.dist-info/top_level.txt
