Metadata-Version: 2.0
Name: AAUtility
Version: 1.0.2
Summary: package utility function in common package
Home-page: https://github.com/gauravccloud/AAUtility.git
Author: Gaurav Sharma
Author-email: gauravdbdev@gmail.com
License: MIT
Platform: UNKNOWN
